aiodag
